forensic_auto_capture/__init__.py
forensic_auto_capture/auto_forensics.py
forensic_auto_capture/disk_functions/__init__.py
forensic_auto_capture/disk_functions/construct.py
forensic_auto_capture/disk_functions/assets/__init__.py
forensic_auto_capture/disk_functions/assets/check_copy_snapshot/__init__.py
forensic_auto_capture/disk_functions/assets/check_copy_snapshot/lambda_function.py
forensic_auto_capture/disk_functions/assets/check_snapshot/__init__.py
forensic_auto_capture/disk_functions/assets/check_snapshot/lambda_function.py
forensic_auto_capture/disk_functions/assets/copy_snapshot/__init__.py
forensic_auto_capture/disk_functions/assets/copy_snapshot/lambda_function.py
forensic_auto_capture/disk_functions/assets/create_snapshot/__init__.py
forensic_auto_capture/disk_functions/assets/create_snapshot/lambda_function.py
forensic_auto_capture/disk_functions/assets/create_volume/__init__.py
forensic_auto_capture/disk_functions/assets/create_volume/lambda_function.py
forensic_auto_capture/disk_functions/assets/final_check_snapshot/__init__.py
forensic_auto_capture/disk_functions/assets/final_check_snapshot/lambda_function.py
forensic_auto_capture/disk_functions/assets/final_copy_snapshot/__init__.py
forensic_auto_capture/disk_functions/assets/final_copy_snapshot/lambda_function.py
forensic_auto_capture/disk_functions/assets/mount_volume/__init__.py
forensic_auto_capture/disk_functions/assets/mount_volume/lambda_function.py
forensic_auto_capture/disk_functions/assets/run_instances/__init__.py
forensic_auto_capture/disk_functions/assets/run_instances/lambda_function.py
forensic_auto_capture/disk_functions/assets/share_snapshot/__init__.py
forensic_auto_capture/disk_functions/assets/share_snapshot/lambda_function.py
forensic_auto_capture/forensics_resources/__init__.py
forensic_auto_capture/forensics_resources/construct.py
forensic_auto_capture/invoke/__init__.py
forensic_auto_capture/invoke/construct.py
forensic_auto_capture/invoke/assets/__init__.py
auto_aws_forensics-0.2.15.dist-info/METADATA
auto_aws_forensics-0.2.15.dist-info/WHEEL
auto_aws_forensics-0.2.15.dist-info/top_level.txt
auto_aws_forensics-0.2.15.dist-info/RECORD
