Metadata-Version: 2.1
Name: auto-aws-forensics
Version: 0.2.15
Summary: Automates the process of creating a forensics capture of an EC2
Author: Shaun McCullough
Classifier: Development Status :: 4 - Beta
Classifier: Intended Audience :: Developers
Classifier: License :: OSI Approved :: Apache Software License
Classifier: Programming Language :: JavaScript
Classifier: Programming Language :: Python :: 3 :: Only
Classifier: Programming Language :: Python :: 3.6
Classifier: Programming Language :: Python :: 3.7
Classifier: Programming Language :: Python :: 3.8
Classifier: Framework :: AWS CDK
Classifier: Topic :: Software Development :: Code Generators
Classifier: Topic :: Utilities
Classifier: Typing :: Typed
Requires-Python: >=3.6
Requires-Dist: aws-cdk.core (>=1.122.0)
Requires-Dist: aws-cdk.aws-ec2 (>=1.122.0)
Requires-Dist: aws-cdk.aws-lambda (>=1.122.0)
Requires-Dist: aws-cdk.aws-stepfunctions (>=1.22.0)
Requires-Dist: aws-cdk.aws-stepfunctions-tasks (>=1.22.0)
Requires-Dist: aws-cdk.aws-events-targets (>=1.22.0)
Requires-Dist: aws-cdk.aws-imagebuilder (>=1.22.0)
Requires-Dist: aws-cdk.aws-s3 (>=1.22.0)
Requires-Dist: aws-cdk.aws-logs (>=1.22.0)
Requires-Dist: aws-cdk.aws-s3-assets (>=1.22.0)
Requires-Dist: aws-cdk.aws-iam (>=1.22.0)
Requires-Dist: aws-cdk.aws-kms (>=1.22.0)
Requires-Dist: aws-cdk.aws-events (>=1.22.0)
Provides-Extra: dev
Requires-Dist: pytest ; extra == 'dev'
Requires-Dist: pylint ; extra == 'dev'
Requires-Dist: twine ; extra == 'dev'
Requires-Dist: moto ; extra == 'dev'
Requires-Dist: boto3 ; extra == 'dev'
Requires-Dist: botocore ; extra == 'dev'
Requires-Dist: mock ; extra == 'dev'
